setup.py
sgizmo/__init__.py
sgizmo/setup.py
sgizmo/sgizmo.py
sgizmo.egg-info/PKG-INFO
sgizmo.egg-info/SOURCES.txt
sgizmo.egg-info/dependency_links.txt
sgizmo.egg-info/not-zip-safe
sgizmo.egg-info/top_level.txt