Metadata-Version: 1.0
Name: sgizmo
Version: 0.3.0
Summary: SurveyGizmo API get calls (API v5)
Home-page: https://github.com/GCCree/sgizmo.git
Author: GCCree
Author-email: gccree@gmail.com
License: MIT
Platform: UNKNOWN
